gooddata_dbt/__init__.py
gooddata_dbt/_version.py
gooddata_dbt/args.py
gooddata_dbt/dbt_plugin.py
gooddata_dbt/logger.py
gooddata_dbt/sdk_wrapper.py
gooddata_dbt/utils.py
gooddata_dbt/dbt/__init__.py
gooddata_dbt/dbt/base.py
gooddata_dbt/dbt/cloud.py
gooddata_dbt/dbt/environment.py
gooddata_dbt/dbt/metrics.py
gooddata_dbt/dbt/profiles.py
gooddata_dbt/dbt/tables.py
gooddata_dbt/gooddata/__init__.py
gooddata_dbt/gooddata/api_wrapper.py
gooddata_dbt/gooddata/config.py
gooddata_dbt-1.58.0.dist-info/METADATA
gooddata_dbt-1.58.0.dist-info/WHEEL
gooddata_dbt-1.58.0.dist-info/entry_points.txt
gooddata_dbt-1.58.0.dist-info/licenses/LICENSE.txt
gooddata_dbt-1.58.0.dist-info/RECORD
