Metadata-Version: 2.4
Name: gooddata-dbt
Version: 1.58.0
Summary: dbt plugin for GoodData
Author-email: GoodData <support@gooddata.com>
License-Expression: MIT
License-File: LICENSE.txt
Classifier: Development Status :: 4 - Beta
Classifier: Environment :: Console
Classifier: Programming Language :: Python :: 3.10
Classifier: Programming Language :: Python :: 3.11
Classifier: Programming Language :: Python :: 3.12
Classifier: Programming Language :: Python :: 3.13
Classifier: Programming Language :: Python :: 3.14
Classifier: Topic :: Database
Classifier: Topic :: Scientific/Engineering
Classifier: Topic :: Software Development
Classifier: Typing :: Typed
Requires-Python: >=3.10
Requires-Dist: attrs<=24.2.0,>=21.4.0
Requires-Dist: cattrs<=24.1.1,>=22.1.0
Requires-Dist: gooddata-sdk~=1.58.0
Requires-Dist: pyyaml>=6.0
Requires-Dist: requests~=2.32.0
Requires-Dist: tabulate~=0.8.10
